yuvtools/__init__.py
yuvtools/bdrate.py
yuvtools/psnr.py
yuvtools/yuv.py
yuvtools-0.0.1.dist-info/LICENSE
yuvtools-0.0.1.dist-info/METADATA
yuvtools-0.0.1.dist-info/WHEEL
yuvtools-0.0.1.dist-info/top_level.txt
yuvtools-0.0.1.dist-info/RECORD
