Metadata-Version: 2.1
Name: yuvtools
Version: 0.0.1
Summary: PSNR/BD-Rate with YUV Files
Home-page: https://github.com/brayden-jo/yuvtools
Author: Brayden Jo
Author-email: brayden.jo@outlook.com
License: MIT
Platform: UNKNOWN
Requires-Dist: scipy
Requires-Dist: opencv-python
